nonebot_plugin_60s/__init__.py
nonebot_plugin_60s/config.py
nonebot_plugin_60s-0.2.0.dist-info/LICENSE
nonebot_plugin_60s-0.2.0.dist-info/METADATA
nonebot_plugin_60s-0.2.0.dist-info/WHEEL
nonebot_plugin_60s-0.2.0.dist-info/RECORD
